ntnx_iam_py_client/__init__.py
ntnx_iam_py_client/api_client.py
ntnx_iam_py_client/api_response.py
ntnx_iam_py_client/configuration.py
ntnx_iam_py_client/custom_retry.py
ntnx_iam_py_client/rest.py
ntnx_iam_py_client/api/__init__.py
ntnx_iam_py_client/api/authorization_policies_api.py
ntnx_iam_py_client/api/certificate_authentication_providers_api.py
ntnx_iam_py_client/api/clients_api.py
ntnx_iam_py_client/api/directory_services_api.py
ntnx_iam_py_client/api/entities_api.py
ntnx_iam_py_client/api/operations_api.py
ntnx_iam_py_client/api/roles_api.py
ntnx_iam_py_client/api/saml_identity_providers_api.py
ntnx_iam_py_client/api/user_groups_api.py
ntnx_iam_py_client/api/users_api.py
ntnx_iam_py_client/models/__init__.py
ntnx_iam_py_client/models/OneOfcommon/__init__.py
ntnx_iam_py_client/models/OneOfcommon/v1/__init__.py
ntnx_iam_py_client/models/OneOfcommon/v1/config/KVPairvalue.py
ntnx_iam_py_client/models/OneOfcommon/v1/config/__init__.py
ntnx_iam_py_client/models/OneOfiam/__init__.py
ntnx_iam_py_client/models/OneOfiam/v4/__init__.py
ntnx_iam_py_client/models/OneOfiam/v4/authn/ActivateUserApiResponsedata.py
ntnx_iam_py_client/models/OneOfiam/v4/authn/ChangeUserPasswordApiResponsedata.py
ntnx_iam_py_client/models/OneOfiam/v4/authn/ConnectionDirectoryServiceApiResponsedata.py
ntnx_iam_py_client/models/OneOfiam/v4/authn/CreateCertAuthProviderApiResponsedata.py
ntnx_iam_py_client/models/OneOfiam/v4/authn/CreateDirectoryServiceApiResponsedata.py
ntnx_iam_py_client/models/OneOfiam/v4/authn/CreateKeyApiResponsedata.py
ntnx_iam_py_client/models/OneOfiam/v4/authn/CreateSamlIdentityProviderApiResponsedata.py
ntnx_iam_py_client/models/OneOfiam/v4/authn/CreateUserApiResponsedata.py
ntnx_iam_py_client/models/OneOfiam/v4/authn/CreateUserGroupApiResponsedata.py
ntnx_iam_py_client/models/OneOfiam/v4/authn/CreateUserKeyApiResponsedata.py
ntnx_iam_py_client/models/OneOfiam/v4/authn/DeleteCertAuthProviderApiResponsedata.py
ntnx_iam_py_client-4.0.1.dist-info/LICENSE.txt
ntnx_iam_py_client-4.0.1.dist-info/METADATA
ntnx_iam_py_client-4.0.1.dist-info/WHEEL
ntnx_iam_py_client-4.0.1.dist-info/top_level.txt
ntnx_iam_py_client-4.0.1.dist-info/RECORD
